{
  "main": {
    "id": "ce91c4294e9a5c02",
    "type": "split",
    "children": [
      {
        "id": "fabfd6ab70ac3c82",
        "type": "tabs",
        "children": [
          {
            "id": "407afd4b979e8318",
            "type": "leaf",
            "state": {
              "type": "markdown",
              "state": {
                "file": "infra/git.md",
                "mode": "source",
                "source": false
              }
            }
          },
          {
            "id": "276875957fe20ae5",
            "type": "leaf",
            "state": {
              "type": "markdown",
              "state": {
                "file": "infra/Docker/Docker.md",
                "mode": "source",
                "source": false
              }
            }
          },
          {
            "id": "6a86d8ade6284974",
            "type": "leaf",
            "state": {
              "type": "markdown",
              "state": {
                "file": "DataLake/Apache Kafka/test.md",
                "mode": "source",
                "source": false
              }
            }
          },
          {
            "id": "a54462a048570516",
            "type": "leaf",
            "state": {
              "type": "release-notes",
              "state": {
                "currentVersion": "1.0.3"
              }
            }
          }
        ],
        "currentTab": 2
      }
    ],
    "direction": "vertical"
  },
  "left": {
    "id": "e2e3b34e911aecf7",
    "type": "split",
    "children": [
      {
        "id": "29e1706dcbf6029c",
        "type": "tabs",
        "children": [
          {
            "id": "e597234f70020723",
            "type": "leaf",
            "state": {
              "type": "file-explorer",
              "state": {
                "sortOrder": "alphabetical"
              }
            }
          },
          {
            "id": "b76da68006098587",
            "type": "leaf",
            "state": {
              "type": "search",
              "state": {
                "query": "itertuple",
                "matchingCase": false,
                "explainSearch": false,
                "collapseAll": false,
                "extraContext": false,
                "sortOrder": "alphabetical"
              }
            }
          },
          {
            "id": "92f61a7c3a5f7271",
            "type": "leaf",
            "state": {
              "type": "starred",
              "state": {}
            }
          }
        ]
      }
    ],
    "direction": "horizontal",
    "width": 274.5
  },
  "right": {
    "id": "e36a518f57cfbb8b",
    "type": "split",
    "children": [
      {
        "id": "a5017f8e461a021c",
        "type": "tabs",
        "children": [
          {
            "id": "bb46c5a6bdfa159b",
            "type": "leaf",
            "state": {
              "type": "backlink",
              "state": {
                "file": "DataLake/Apache Kafka/test.md",
                "collapseAll": false,
                "extraContext": false,
                "sortOrder": "alphabetical",
                "showSearch": false,
                "searchQuery": "",
                "backlinkCollapsed": false,
                "unlinkedCollapsed": true
              }
            }
          },
          {
            "id": "d09af98b0262bc4f",
            "type": "leaf",
            "state": {
              "type": "outgoing-link",
              "state": {
                "file": "DataLake/Apache Kafka/test.md",
                "linksCollapsed": false,
                "unlinkedCollapsed": true
              }
            }
          },
          {
            "id": "684b89321bce6aeb",
            "type": "leaf",
            "state": {
              "type": "tag",
              "state": {
                "sortOrder": "frequency",
                "useHierarchy": true
              }
            }
          },
          {
            "id": "a6897533a43ddcc4",
            "type": "leaf",
            "state": {
              "type": "outline",
              "state": {
                "file": "DataLake/Apache Kafka/test.md"
              }
            }
          },
          {
            "id": "3def5e24c0fc2b46",
            "type": "leaf",
            "state": {
              "type": "advanced-tables-toolbar",
              "state": {}
            }
          }
        ],
        "currentTab": 4
      }
    ],
    "direction": "horizontal",
    "width": 300
  },
  "active": "6a86d8ade6284974",
  "lastOpenFiles": [
    "DataLake/Apache Kafka/로컬 싱글브로커 테스트.md",
    "infra/Docker/Docker.md",
    "DataLake/Apache Kafka/test.md",
    "infra/vim.md",
    "infra/git.md",
    "DataLake/hadoop ecosystem/Hive/HiveQL.md",
    "Language/Pandas.md",
    "MLOPS/아키텍쳐.md",
    "계정들.md",
    "MLOPS/디자인패턴.md"
  ]
}